{
  "globalChoiceSets": [],
  "entities": [
    {
      "@odata.type": "Microsoft.Dynamics.CRM.EntityMetadata",
      "LogicalName": "mmd_product",
      "SchemaName": "mmd_Product",
      "DisplayName": {
        "LocalizedLabels": [
          {
            "Label": "Product",
            "LanguageCode": 1033
          }
        ]
      },
      "DisplayCollectionName": {
        "LocalizedLabels": [
          {
            "Label": "Products",
            "LanguageCode": 1033
          }
        ]
      },
      "Description": {
        "LocalizedLabels": [
          {
            "Label": "Entity generated from Mermaid ERD: Product",
            "LanguageCode": 1033
          }
        ]
      },
      "OwnershipType": "UserOwned",
      "IsActivity": false,
      "HasNotes": false,
      "HasActivities": false,
      "Attributes": [
        {
          "LogicalName": "mmd_name",
          "SchemaName": "mmd_Name",
          "DisplayName": {
            "LocalizedLabels": [
              {
                "Label": "Id",
                "LanguageCode": 1033
              }
            ]
          },
          "RequiredLevel": {
            "Value": "None",
            "CanBeChanged": true,
            "ManagedPropertyLogicalName": "canmodifyrequirementlevelsettings"
          },
          "Description": {
            "LocalizedLabels": [
              {
                "Label": "Primary name field",
                "LanguageCode": 1033
              }
            ]
          },
          "@odata.type": "Microsoft.Dynamics.CRM.StringAttributeMetadata",
          "AttributeType": "String",
          "AttributeTypeName": {
            "Value": "StringType"
          },
          "MaxLength": 100,
          "IsPrimaryName": true,
          "FormatName": {
            "Value": "Text"
          }
        }
      ]
    },
    {
      "@odata.type": "Microsoft.Dynamics.CRM.EntityMetadata",
      "LogicalName": "mmd_order",
      "SchemaName": "mmd_Order",
      "DisplayName": {
        "LocalizedLabels": [
          {
            "Label": "Order",
            "LanguageCode": 1033
          }
        ]
      },
      "DisplayCollectionName": {
        "LocalizedLabels": [
          {
            "Label": "Orders",
            "LanguageCode": 1033
          }
        ]
      },
      "Description": {
        "LocalizedLabels": [
          {
            "Label": "Entity generated from Mermaid ERD: Order",
            "LanguageCode": 1033
          }
        ]
      },
      "OwnershipType": "UserOwned",
      "IsActivity": false,
      "HasNotes": false,
      "HasActivities": false,
      "Attributes": [
        {
          "LogicalName": "mmd_name",
          "SchemaName": "mmd_Name",
          "DisplayName": {
            "LocalizedLabels": [
              {
                "Label": "Id",
                "LanguageCode": 1033
              }
            ]
          },
          "RequiredLevel": {
            "Value": "None",
            "CanBeChanged": true,
            "ManagedPropertyLogicalName": "canmodifyrequirementlevelsettings"
          },
          "Description": {
            "LocalizedLabels": [
              {
                "Label": "Primary name field",
                "LanguageCode": 1033
              }
            ]
          },
          "@odata.type": "Microsoft.Dynamics.CRM.StringAttributeMetadata",
          "AttributeType": "String",
          "AttributeTypeName": {
            "Value": "StringType"
          },
          "MaxLength": 100,
          "IsPrimaryName": true,
          "FormatName": {
            "Value": "Text"
          }
        }
      ]
    }
  ],
  "relationships": [],
  "additionalColumns": [
    {
      "entityLogicalName": "mmd_product",
      "columnMetadata": {
        "LogicalName": "mmd_name",
        "SchemaName": "mmd_Name",
        "DisplayName": {
          "LocalizedLabels": [
            {
              "Label": "Name",
              "LanguageCode": 1033
            }
          ]
        },
        "RequiredLevel": {
          "Value": "None"
        },
        "Description": {
          "LocalizedLabels": [
            {
              "Label": "Name field",
              "LanguageCode": 1033
            }
          ]
        },
        "@odata.type": "Microsoft.Dynamics.CRM.StringAttributeMetadata",
        "AttributeType": "String",
        "AttributeTypeName": {
          "Value": "StringType"
        },
        "FormatName": {
          "Value": "Text"
        },
        "MaxLength": 100
      }
    },
    {
      "entityLogicalName": "mmd_product",
      "columnMetadata": {
        "LogicalName": "mmd_color",
        "SchemaName": "mmd_Color",
        "DisplayName": {
          "LocalizedLabels": [
            {
              "Label": "Color",
              "LanguageCode": 1033
            }
          ]
        },
        "RequiredLevel": {
          "Value": "None"
        },
        "Description": {
          "LocalizedLabels": [
            {
              "Label": "Color field",
              "LanguageCode": 1033
            }
          ]
        },
        "@odata.type": "Microsoft.Dynamics.CRM.PicklistAttributeMetadata",
        "AttributeType": "Picklist",
        "AttributeTypeName": {
          "Value": "PicklistType"
        },
        "_globalChoiceSetName": "mmd_color"
      }
    },
    {
      "entityLogicalName": "mmd_product",
      "columnMetadata": {
        "LogicalName": "mmd_size",
        "SchemaName": "mmd_Size",
        "DisplayName": {
          "LocalizedLabels": [
            {
              "Label": "Size",
              "LanguageCode": 1033
            }
          ]
        },
        "RequiredLevel": {
          "Value": "None"
        },
        "Description": {
          "LocalizedLabels": [
            {
              "Label": "Size field",
              "LanguageCode": 1033
            }
          ]
        },
        "@odata.type": "Microsoft.Dynamics.CRM.PicklistAttributeMetadata",
        "AttributeType": "Picklist",
        "AttributeTypeName": {
          "Value": "PicklistType"
        },
        "_globalChoiceSetName": "mmd_size"
      }
    },
    {
      "entityLogicalName": "mmd_product",
      "columnMetadata": {
        "LogicalName": "mmd_price",
        "SchemaName": "mmd_Price",
        "DisplayName": {
          "LocalizedLabels": [
            {
              "Label": "Price",
              "LanguageCode": 1033
            }
          ]
        },
        "RequiredLevel": {
          "Value": "None"
        },
        "Description": {
          "LocalizedLabels": [
            {
              "Label": "Price field",
              "LanguageCode": 1033
            }
          ]
        },
        "@odata.type": "Microsoft.Dynamics.CRM.MoneyAttributeMetadata",
        "AttributeType": "Money",
        "AttributeTypeName": {
          "Value": "MoneyType"
        },
        "MinValue": -922337203685477,
        "MaxValue": 922337203685477,
        "Precision": 4,
        "PrecisionSource": 2
      }
    },
    {
      "entityLogicalName": "mmd_product",
      "columnMetadata": {
        "LogicalName": "mmd_active",
        "SchemaName": "mmd_Active",
        "DisplayName": {
          "LocalizedLabels": [
            {
              "Label": "Active",
              "LanguageCode": 1033
            }
          ]
        },
        "RequiredLevel": {
          "Value": "None"
        },
        "Description": {
          "LocalizedLabels": [
            {
              "Label": "Active field",
              "LanguageCode": 1033
            }
          ]
        },
        "@odata.type": "Microsoft.Dynamics.CRM.BooleanAttributeMetadata",
        "AttributeType": "Boolean",
        "AttributeTypeName": {
          "Value": "BooleanType"
        },
        "OptionSet": {
          "TrueOption": {
            "Value": 1,
            "Label": {
              "LocalizedLabels": [
                {
                  "Label": "Yes",
                  "LanguageCode": 1033
                }
              ]
            }
          },
          "FalseOption": {
            "Value": 0,
            "Label": {
              "LocalizedLabels": [
                {
                  "Label": "No",
                  "LanguageCode": 1033
                }
              ]
            }
          }
        }
      }
    },
    {
      "entityLogicalName": "mmd_order",
      "columnMetadata": {
        "LogicalName": "mmd_status",
        "SchemaName": "mmd_Status",
        "DisplayName": {
          "LocalizedLabels": [
            {
              "Label": "Status",
              "LanguageCode": 1033
            }
          ]
        },
        "RequiredLevel": {
          "Value": "None"
        },
        "Description": {
          "LocalizedLabels": [
            {
              "Label": "Status field",
              "LanguageCode": 1033
            }
          ]
        },
        "@odata.type": "Microsoft.Dynamics.CRM.PicklistAttributeMetadata",
        "AttributeType": "Picklist",
        "AttributeTypeName": {
          "Value": "PicklistType"
        },
        "_globalChoiceSetName": "mmd_status"
      }
    },
    {
      "entityLogicalName": "mmd_order",
      "columnMetadata": {
        "LogicalName": "mmd_order_date",
        "SchemaName": "mmd_OrderDate",
        "DisplayName": {
          "LocalizedLabels": [
            {
              "Label": "Order Date",
              "LanguageCode": 1033
            }
          ]
        },
        "RequiredLevel": {
          "Value": "None"
        },
        "Description": {
          "LocalizedLabels": [
            {
              "Label": "Order Date field",
              "LanguageCode": 1033
            }
          ]
        },
        "@odata.type": "Microsoft.Dynamics.CRM.DateTimeAttributeMetadata",
        "AttributeType": "DateTime",
        "AttributeTypeName": {
          "Value": "DateTimeType"
        },
        "Format": "DateAndTime",
        "DateTimeBehavior": {
          "Value": "UserLocal"
        }
      }
    },
    {
      "entityLogicalName": "mmd_order",
      "columnMetadata": {
        "LogicalName": "mmd_customer_email",
        "SchemaName": "mmd_CustomerEmail",
        "DisplayName": {
          "LocalizedLabels": [
            {
              "Label": "Customer Email",
              "LanguageCode": 1033
            }
          ]
        },
        "RequiredLevel": {
          "Value": "None"
        },
        "Description": {
          "LocalizedLabels": [
            {
              "Label": "Customer Email field",
              "LanguageCode": 1033
            }
          ]
        },
        "@odata.type": "Microsoft.Dynamics.CRM.StringAttributeMetadata",
        "AttributeType": "String",
        "AttributeTypeName": {
          "Value": "StringType"
        },
        "FormatName": {
          "Value": "Email"
        },
        "MaxLength": 100
      }
    }
  ],
  "metadata": {
    "publisherPrefix": "mmd",
    "generatedAt": "2025-07-26T13:52:37.563Z",
    "source": "mermaid-erd"
  }
}